[
  {
    "app.user_data.MorphEffectData": {
      "_FieldOtomonEpvsID": 2,
      "_FieldEnemyEpvsID": 2,
      "_BattleOtomonEpvsID": 2,
      "_BattleEnemyEpvsID": 2,
      "_MorphEffectList": [
        {
          "app.user_data.MorphEffectData.cMorphParam": {
            "_MorphID": "[463439776] ID_BTL_MORPH_CHG_NORMAL",
            "_MorphVisualID": "[3507608448] ID_MORPH_VISUAL_NORMAL",
            "_MotionChangeEnabled": false,
            "_OtomonEffect": [],
            "_EnemyEffect": [],
            "_McdList": [
              {
                "app.user_data.MorphEffectData.cModelParam": {
                  "_PartsID": "[997777664] ID_PARTS_DAMMY",
                  "_PartsID2": "[997777664] ID_PARTS_DAMMY",
                  "_ConditionGuid": "0c4a2359-0b4a-4451-a0e6-23dfe66c4271",
                  "_BrokenConditionGuid": "00000000-0000-0000-0000-000000000000"
                }
              },
              {
                "app.user_data.MorphEffectData.cModelParam": {
                  "_PartsID": "[997777664] ID_PARTS_DAMMY",
                  "_PartsID2": "[997777664] ID_PARTS_DAMMY",
                  "_ConditionGuid": "861aa7d4-f6a4-4790-9094-b4f7367ccef2",
                  "_BrokenConditionGuid": "00000000-0000-0000-0000-000000000000"
                }
              },
              {
                "app.user_data.MorphEffectData.cModelParam": {
                  "_PartsID": "[997777664] ID_PARTS_DAMMY",
                  "_PartsID2": "[997777664] ID_PARTS_DAMMY",
                  "_ConditionGuid": "7e9b783f-ae48-4e0a-85d4-6e1ef4ce83b5",
                  "_BrokenConditionGuid": "00000000-0000-0000-0000-000000000000"
                }
              }
            ]
          }
        },
        {
          "app.user_data.MorphEffectData.cMorphParam": {
            "_MorphID": "[140363136] ID_BTL_MORPH_CHG_ANGRY1",
            "_MorphVisualID": "[1106023808] ID_MORPH_VISUAL_ANGRY",
            "_MotionChangeEnabled": false,
            "_OtomonEffect": [],
            "_EnemyEffect": [
              {
                "app.user_data.MorphEffectData.cPartsParam": {
                  "_ElementID": 499,
                  "_PartsID": "[997777664] ID_PARTS_DAMMY",
                  "_PartsID2": "[997777664] ID_PARTS_DAMMY"
                }
              }
            ],
            "_McdList": [
              {
                "app.user_data.MorphEffectData.cModelParam": {
                  "_PartsID": "[997777664] ID_PARTS_DAMMY",
                  "_PartsID2": "[997777664] ID_PARTS_DAMMY",
                  "_ConditionGuid": "34351bfd-3dec-4250-bd5c-c6e89cad1499",
                  "_BrokenConditionGuid": "00000000-0000-0000-0000-000000000000"
                }
              }
            ]
          }
        },
        {
          "app.user_data.MorphEffectData.cMorphParam": {
            "_MorphID": "[4141537904] ID_BTL_MORPH_CHG_DEAD",
            "_MorphVisualID": "[20298] ID_MORPH_VISUAL_DEAD",
            "_MotionChangeEnabled": false,
            "_OtomonEffect": [],
            "_EnemyEffect": [],
            "_McdList": [
              {
                "app.user_data.MorphEffectData.cModelParam": {
                  "_PartsID": "[997777664] ID_PARTS_DAMMY",
                  "_PartsID2": "[997777664] ID_PARTS_DAMMY",
                  "_ConditionGuid": "9e4409bd-186e-4ddf-8f1f-8649318ddcff",
                  "_BrokenConditionGuid": "00000000-0000-0000-0000-000000000000"
                }
              },
              {
                "app.user_data.MorphEffectData.cModelParam": {
                  "_PartsID": "[997777664] ID_PARTS_DAMMY",
                  "_PartsID2": "[997777664] ID_PARTS_DAMMY",
                  "_ConditionGuid": "7e9b783f-ae48-4e0a-85d4-6e1ef4ce83b5",
                  "_BrokenConditionGuid": "00000000-0000-0000-0000-000000000000"
                }
              }
            ]
          }
        },
        {
          "app.user_data.MorphEffectData.cMorphParam": {
            "_MorphID": "[176953568] ID_BTL_MORPH_CHG_SPECIAL1",
            "_MorphVisualID": "[2021870080] ID_MORPH_VISUAL_MO020_NO_SHELL",
            "_MotionChangeEnabled": false,
            "_OtomonEffect": [],
            "_EnemyEffect": [],
            "_McdList": [
              {
                "app.user_data.MorphEffectData.cModelParam": {
                  "_PartsID": "[997777664] ID_PARTS_DAMMY",
                  "_PartsID2": "[997777664] ID_PARTS_DAMMY",
                  "_ConditionGuid": "0c4a2359-0b4a-4451-a0e6-23dfe66c4271",
                  "_BrokenConditionGuid": "00000000-0000-0000-0000-000000000000"
                }
              },
              {
                "app.user_data.MorphEffectData.cModelParam": {
                  "_PartsID": "[997777664] ID_PARTS_DAMMY",
                  "_PartsID2": "[997777664] ID_PARTS_DAMMY",
                  "_ConditionGuid": "1d1410ef-8de0-438d-86e2-a73912d6f401",
                  "_BrokenConditionGuid": "00000000-0000-0000-0000-000000000000"
                }
              },
              {
                "app.user_data.MorphEffectData.cModelParam": {
                  "_PartsID": "[997777664] ID_PARTS_DAMMY",
                  "_PartsID2": "[997777664] ID_PARTS_DAMMY",
                  "_ConditionGuid": "7e9b783f-ae48-4e0a-85d4-6e1ef4ce83b5",
                  "_BrokenConditionGuid": "00000000-0000-0000-0000-000000000000"
                }
              }
            ]
          }
        },
        {
          "app.user_data.MorphEffectData.cMorphParam": {
            "_MorphID": "[3774877408] ID_BTL_MORPH_CNG_SPECIAL2",
            "_MorphVisualID": "[2094665472] ID_MORPH_VISUAL_MO020_SEA_SHELL",
            "_MotionChangeEnabled": true,
            "_OtomonEffect": [],
            "_EnemyEffect": [],
            "_McdList": [
              {
                "app.user_data.MorphEffectData.cModelParam": {
                  "_PartsID": "[997777664] ID_PARTS_DAMMY",
                  "_PartsID2": "[997777664] ID_PARTS_DAMMY",
                  "_ConditionGuid": "0c4a2359-0b4a-4451-a0e6-23dfe66c4271",
                  "_BrokenConditionGuid": "00000000-0000-0000-0000-000000000000"
                }
              },
              {
                "app.user_data.MorphEffectData.cModelParam": {
                  "_PartsID": "[997777664] ID_PARTS_DAMMY",
                  "_PartsID2": "[997777664] ID_PARTS_DAMMY",
                  "_ConditionGuid": "80efd818-3f0a-4514-84cc-c3891a9d4a89",
                  "_BrokenConditionGuid": "00000000-0000-0000-0000-000000000000"
                }
              },
              {
                "app.user_data.MorphEffectData.cModelParam": {
                  "_PartsID": "[656977408] ID_PARTS_EM0020_00_00_2",
                  "_PartsID2": "[997777664] ID_PARTS_DAMMY",
                  "_ConditionGuid": "9fc40985-3b1c-43ef-aa24-e376a3f69248",
                  "_BrokenConditionGuid": "7e9b783f-ae48-4e0a-85d4-6e1ef4ce83b5"
                }
              }
            ]
          }
        }
      ],
      "_MorphVisualList": [
        {
          "app.user_data.MorphEffectData.cMorphParam": {
            "_MorphID": "[2704140672] ID_BTL_MORPH_CHG_NONE",
            "_MorphVisualID": "[1520992000] ID_MORPH_VISUAL_MO020_OT_GRAVI_SHELL_OPEN",
            "_MotionChangeEnabled": true,
            "_OtomonEffect": [],
            "_EnemyEffect": [],
            "_McdList": [
              {
                "app.user_data.MorphEffectData.cModelParam": {
                  "_PartsID": "[997777664] ID_PARTS_DAMMY",
                  "_PartsID2": "[997777664] ID_PARTS_DAMMY",
                  "_ConditionGuid": "0c4a2359-0b4a-4451-a0e6-23dfe66c4271",
                  "_BrokenConditionGuid": "00000000-0000-0000-0000-000000000000"
                }
              },
              {
                "app.user_data.MorphEffectData.cModelParam": {
                  "_PartsID": "[997777664] ID_PARTS_DAMMY",
                  "_PartsID2": "[997777664] ID_PARTS_DAMMY",
                  "_ConditionGuid": "861aa7d4-f6a4-4790-9094-b4f7367ccef2",
                  "_BrokenConditionGuid": "00000000-0000-0000-0000-000000000000"
                }
              },
              {
                "app.user_data.MorphEffectData.cModelParam": {
                  "_PartsID": "[997777664] ID_PARTS_DAMMY",
                  "_PartsID2": "[997777664] ID_PARTS_DAMMY",
                  "_ConditionGuid": "9fc40985-3b1c-43ef-aa24-e376a3f69248",
                  "_BrokenConditionGuid": "00000000-0000-0000-0000-000000000000"
                }
              }
            ]
          }
        },
        {
          "app.user_data.MorphEffectData.cMorphParam": {
            "_MorphID": "[2704140672] ID_BTL_MORPH_CHG_NONE",
            "_MorphVisualID": "[2947196672] ID_MORPH_VISUAL_MO020_SICKLE_OPEN",
            "_MotionChangeEnabled": false,
            "_OtomonEffect": [],
            "_EnemyEffect": [],
            "_McdList": [
              {
                "app.user_data.MorphEffectData.cModelParam": {
                  "_PartsID": "[997777664] ID_PARTS_DAMMY",
                  "_PartsID2": "[997777664] ID_PARTS_DAMMY",
                  "_ConditionGuid": "9fc40985-3b1c-43ef-aa24-e376a3f69248",
                  "_BrokenConditionGuid": "00000000-0000-0000-0000-000000000000"
                }
              }
            ]
          }
        },
        {
          "app.user_data.MorphEffectData.cMorphParam": {
            "_MorphID": "[2704140672] ID_BTL_MORPH_CHG_NONE",
            "_MorphVisualID": "[3998519360] ID_MORPH_VISUAL_MO020_SICKLE_CLOSE",
            "_MotionChangeEnabled": false,
            "_OtomonEffect": [],
            "_EnemyEffect": [],
            "_McdList": [
              {
                "app.user_data.MorphEffectData.cModelParam": {
                  "_PartsID": "[997777664] ID_PARTS_DAMMY",
                  "_PartsID2": "[997777664] ID_PARTS_DAMMY",
                  "_ConditionGuid": "7e9b783f-ae48-4e0a-85d4-6e1ef4ce83b5",
                  "_BrokenConditionGuid": "00000000-0000-0000-0000-000000000000"
                }
              }
            ]
          }
        }
      ],
      "_OtomonLinkList": [
        {
          "app.user_data.MorphEffectData.cStatusMorphLinkData": {
            "_Status": "[2398810112] SKL_STATUS_ALL_ATK_UP",
            "_MorphID": "[1520992000] ID_MORPH_VISUAL_MO020_OT_GRAVI_SHELL_OPEN"
          }
        },
        {
          "app.user_data.MorphEffectData.cStatusMorphLinkData": {
            "_Status": "[2435135872] SKL_STATUS_WATER_ATK_UP",
            "_MorphID": "[1520992000] ID_MORPH_VISUAL_MO020_OT_GRAVI_SHELL_OPEN"
          }
        }
      ]
    }
  }
]