[
  {
    "app.user_data.ArmorColorData": {
      "index": 25,
      "_ParamList": {
        "app.cEnumerableParam`2<app.ArmorDef.SERIES_ID_Fixed,app.user_data.ArmorColorData.cParam>": {
          "index": 24,
          "_ParamList": [
            {
              "app.user_data.ArmorColorData.cParam": {
                "index": 1,
                "_EnumValue": 83811568,
                "_DefaultBaseColor": [
                  -1.8748891093615894e+38
                ],
                "_DefaultSubColor": [
                  -1.9691420752620468e+38
                ],
                "_DefaultBaseColorFemale": [
                  0.0
                ],
                "_DefaultSubColorFemale": [
                  0.0
                ]
              }
            },
            {
              "app.user_data.ArmorColorData.cParam": {
                "index": 2,
                "_EnumValue": 1351073024,
                "_DefaultBaseColor": [
                  -1.942504781081379e+38
                ],
                "_DefaultSubColor": [
                  -3.2509297178081175e+38
                ],
                "_DefaultBaseColorFemale": [
                  0.0
                ],
                "_DefaultSubColorFemale": [
                  0.0
                ]
              }
            },
            {
              "app.user_data.ArmorColorData.cParam": {
                "index": 3,
                "_EnumValue": -1357467904,
                "_DefaultBaseColor": [
                  -1.9148917001746795e+38
                ],
                "_DefaultSubColor": [
                  -2.3832900167276825e+38
                ],
                "_DefaultBaseColorFemale": [
                  0.0
                ],
                "_DefaultSubColorFemale": [
                  0.0
                ]
              }
            },
            {
              "app.user_data.ArmorColorData.cParam": {
                "index": 4,
                "_EnumValue": -818226688,
                "_DefaultBaseColor": [
                  NaN
                ],
                "_DefaultSubColor": [
                  NaN
                ],
                "_DefaultBaseColorFemale": [
                  0.0
                ],
                "_DefaultSubColorFemale": [
                  0.0
                ]
              }
            },
            {
              "app.user_data.ArmorColorData.cParam": {
                "index": 5,
                "_EnumValue": -961460160,
                "_DefaultBaseColor": [
                  -2.0083487843222896e+38
                ],
                "_DefaultSubColor": [
                  -1.7681859891500264e+38
                ],
                "_DefaultBaseColorFemale": [
                  -2.8344600489151517e+38
                ],
                "_DefaultSubColorFemale": [
                  0.0
                ]
              }
            },
            {
              "app.user_data.ArmorColorData.cParam": {
                "index": 6,
                "_EnumValue": -1230086528,
                "_DefaultBaseColor": [
                  -1.8503859303194178e+38
                ],
                "_DefaultSubColor": [
                  -2.7422746718496906e+38
                ],
                "_DefaultBaseColorFemale": [
                  0.0
                ],
                "_DefaultSubColorFemale": [
                  0.0
                ]
              }
            },
            {
              "app.user_data.ArmorColorData.cParam": {
                "index": 7,
                "_EnumValue": 1483321472,
                "_DefaultBaseColor": [
                  -2.2880610612770974e+38
                ],
                "_DefaultSubColor": [
                  -2.7422746718496906e+38
                ],
                "_DefaultBaseColorFemale": [
                  0.0
                ],
                "_DefaultSubColorFemale": [
                  0.0
                ]
              }
            },
            {
              "app.user_data.ArmorColorData.cParam": {
                "index": 8,
                "_EnumValue": 264711632,
                "_DefaultBaseColor": [
                  NaN
                ],
                "_DefaultSubColor": [
                  -2.503187655682805e+38
                ],
                "_DefaultBaseColorFemale": [
                  0.0
                ],
                "_DefaultSubColorFemale": [
                  0.0
                ]
              }
            },
            {
              "app.user_data.ArmorColorData.cParam": {
                "index": 9,
                "_EnumValue": -1547998080,
                "_DefaultBaseColor": [
                  -3.2324670459941054e+38
                ],
                "_DefaultSubColor": [
                  -1.8799775602829535e+38
                ],
                "_DefaultBaseColorFemale": [
                  0.0
                ],
                "_DefaultSubColorFemale": [
                  0.0
                ]
              }
            },
            {
              "app.user_data.ArmorColorData.cParam": {
                "index": 10,
                "_EnumValue": -1069266944,
                "_DefaultBaseColor": [
                  -3.3969091157448638e+38
                ],
                "_DefaultSubColor": [
                  -1.848043717658388e+38
                ],
                "_DefaultBaseColorFemale": [
                  -1.861567419909815e+38
                ],
                "_DefaultSubColorFemale": [
                  0.0
                ]
              }
            },
            {
              "app.user_data.ArmorColorData.cParam": {
                "index": 11,
                "_EnumValue": 752285312,
                "_DefaultBaseColor": [
                  -1.915289235402911e+38
                ],
                "_DefaultSubColor": [
                  -2.9655347153305586e+38
                ],
                "_DefaultBaseColorFemale": [
                  0.0
                ],
                "_DefaultSubColorFemale": [
                  0.0
                ]
              }
            },
            {
              "app.user_data.ArmorColorData.cParam": {
                "index": 12,
                "_EnumValue": 908327744,
                "_DefaultBaseColor": [
                  -2.9324908164283853e+38
                ],
                "_DefaultSubColor": [
                  -2.0938346786715686e+38
                ],
                "_DefaultBaseColorFemale": [
                  0.0
                ],
                "_DefaultSubColorFemale": [
                  0.0
                ]
              }
            },
            {
              "app.user_data.ArmorColorData.cParam": {
                "index": 13,
                "_EnumValue": -447393856,
                "_DefaultBaseColor": [
                  -2.0876704487448268e+38
                ],
                "_DefaultSubColor": [
                  -1.8094320944959164e+38
                ],
                "_DefaultBaseColorFemale": [
                  -1.834984685410981e+38
                ],
                "_DefaultSubColorFemale": [
                  -2.1938514997331918e+38
                ]
              }
            },
            {
              "app.user_data.ArmorColorData.cParam": {
                "index": 14,
                "_EnumValue": -1160116736,
                "_DefaultBaseColor": [
                  -1.8882852352566092e+38
                ],
                "_DefaultSubColor": [
                  -3.3567957829753377e+38
                ],
                "_DefaultBaseColorFemale": [
                  0.0
                ],
                "_DefaultSubColorFemale": [
                  0.0
                ]
              }
            },
            {
              "app.user_data.ArmorColorData.cParam": {
                "index": 15,
                "_EnumValue": 404886496,
                "_DefaultBaseColor": [
                  -3.287918951026393e+38
                ],
                "_DefaultSubColor": [
                  -1.8217366211060677e+38
                ],
                "_DefaultBaseColorFemale": [
                  0.0
                ],
                "_DefaultSubColorFemale": [
                  0.0
                ]
              }
            },
            {
              "app.user_data.ArmorColorData.cParam": {
                "index": 16,
                "_EnumValue": 1363842048,
                "_DefaultBaseColor": [
                  -1.8748891093615894e+38
                ],
                "_DefaultSubColor": [
                  -2.2080256588606077e+38
                ],
                "_DefaultBaseColorFemale": [
                  0.0
                ],
                "_DefaultSubColorFemale": [
                  0.0
                ]
              }
            },
            {
              "app.user_data.ArmorColorData.cParam": {
                "index": 17,
                "_EnumValue": -680644352,
                "_DefaultBaseColor": [
                  -1.808169514498089e+38
                ],
                "_DefaultSubColor": [
                  -1.9160123033052813e+38
                ],
                "_DefaultBaseColorFemale": [
                  0.0
                ],
                "_DefaultSubColorFemale": [
                  0.0
                ]
              }
            },
            {
              "app.user_data.ArmorColorData.cParam": {
                "index": 18,
                "_EnumValue": 1758665600,
                "_DefaultBaseColor": [
                  -1.9955449047876964e+38
                ],
                "_DefaultSubColor": [
                  NaN
                ],
                "_DefaultBaseColorFemale": [
                  0.0
                ],
                "_DefaultSubColorFemale": [
                  0.0
                ]
              }
            },
            {
              "app.user_data.ArmorColorData.cParam": {
                "index": 19,
                "_EnumValue": 2143492352,
                "_DefaultBaseColor": [
                  -2.969324483565001e+38
                ],
                "_DefaultSubColor": [
                  -1.8082940484930555e+38
                ],
                "_DefaultBaseColorFemale": [
                  0.0
                ],
                "_DefaultSubColorFemale": [
                  0.0
                ]
              }
            },
            {
              "app.user_data.ArmorColorData.cParam": {
                "index": 20,
                "_EnumValue": -1736991744,
                "_DefaultBaseColor": [
                  -1.9947273208565732e+38
                ],
                "_DefaultSubColor": [
                  -2.6226512510724094e+38
                ],
                "_DefaultBaseColorFemale": [
                  0.0
                ],
                "_DefaultSubColorFemale": [
                  0.0
                ]
              }
            },
            {
              "app.user_data.ArmorColorData.cParam": {
                "index": 21,
                "_EnumValue": -1246504832,
                "_DefaultBaseColor": [
                  -2.047848168553113e+38
                ],
                "_DefaultSubColor": [
                  -2.6226512510724094e+38
                ],
                "_DefaultBaseColorFemale": [
                  0.0
                ],
                "_DefaultSubColorFemale": [
                  0.0
                ]
              }
            },
            {
              "app.user_data.ArmorColorData.cParam": {
                "index": 22,
                "_EnumValue": 1003076672,
                "_DefaultBaseColor": [
                  -2.845075862101703e+38
                ],
                "_DefaultSubColor": [
                  -3.3580488302406513e+38
                ],
                "_DefaultBaseColorFemale": [
                  0.0
                ],
                "_DefaultSubColorFemale": [
                  0.0
                ]
              }
            },
            {
              "app.user_data.ArmorColorData.cParam": {
                "index": 23,
                "_EnumValue": 8270,
                "_DefaultBaseColor": [
                  -2.3701322091455056e+38
                ],
                "_DefaultSubColor": [
                  -1.8358655504600675e+38
                ],
                "_DefaultBaseColorFemale": [
                  0.0
                ],
                "_DefaultSubColorFemale": [
                  0.0
                ]
              }
            }
          ]
        }
      }
    }
  }
]