[
  {
    "ace.user_data.ModelPartsInfo2": {
      "_Conditions": [
        {
          "ace.model_parts_manager.cConditionInfo": {
            "_GroupConditions": [
              {
                "ace.model_parts_manager.cGroupCondition": {
                  "_GroupId": "335d1d96-d593-492b-8b70-1904492c610f",
                  "_OptionFlagAllInvisible": false,
                  "_SetIds": [
                    "ce52bafd-b88e-4667-b817-0ff0131139bc"
                  ]
                }
              },
              {
                "ace.model_parts_manager.cGroupCondition": {
                  "_GroupId": "38b2c11f-735f-42cc-a4f1-59cdaafdb712",
                  "_OptionFlagAllInvisible": true,
                  "_SetIds": []
                }
              },
              {
                "ace.model_parts_manager.cGroupCondition": {
                  "_GroupId": "ad90746a-11a6-452a-a4f7-b9967d5f2a02",
                  "_OptionFlagAllInvisible": true,
                  "_SetIds": []
                }
              },
              {
                "ace.model_parts_manager.cGroupCondition": {
                  "_GroupId": "8c735c2d-2701-4880-819b-329a9ca152bb",
                  "_OptionFlagAllInvisible": false,
                  "_SetIds": []
                }
              }
            ],
            "_ChangeType": 1,
            "_ConditionId": "f7e17553-4961-4d00-8049-bb91c3f49f17",
            "_IsDefault": true
          }
        },
        {
          "ace.model_parts_manager.cConditionInfo": {
            "_GroupConditions": [
              {
                "ace.model_parts_manager.cGroupCondition": {
                  "_GroupId": "335d1d96-d593-492b-8b70-1904492c610f",
                  "_OptionFlagAllInvisible": false,
                  "_SetIds": []
                }
              },
              {
                "ace.model_parts_manager.cGroupCondition": {
                  "_GroupId": "38b2c11f-735f-42cc-a4f1-59cdaafdb712",
                  "_OptionFlagAllInvisible": false,
                  "_SetIds": [
                    "051f0cb9-bd06-42e4-855a-2ec0b7c6640a"
                  ]
                }
              },
              {
                "ace.model_parts_manager.cGroupCondition": {
                  "_GroupId": "ad90746a-11a6-452a-a4f7-b9967d5f2a02",
                  "_OptionFlagAllInvisible": false,
                  "_SetIds": []
                }
              },
              {
                "ace.model_parts_manager.cGroupCondition": {
                  "_GroupId": "8c735c2d-2701-4880-819b-329a9ca152bb",
                  "_OptionFlagAllInvisible": false,
                  "_SetIds": []
                }
              }
            ],
            "_ChangeType": 1,
            "_ConditionId": "80478e22-24f7-4408-bc96-a591a911b939",
            "_IsDefault": false
          }
        },
        {
          "ace.model_parts_manager.cConditionInfo": {
            "_GroupConditions": [
              {
                "ace.model_parts_manager.cGroupCondition": {
                  "_GroupId": "335d1d96-d593-492b-8b70-1904492c610f",
                  "_OptionFlagAllInvisible": false,
                  "_SetIds": []
                }
              },
              {
                "ace.model_parts_manager.cGroupCondition": {
                  "_GroupId": "38b2c11f-735f-42cc-a4f1-59cdaafdb712",
                  "_OptionFlagAllInvisible": true,
                  "_SetIds": []
                }
              },
              {
                "ace.model_parts_manager.cGroupCondition": {
                  "_GroupId": "ad90746a-11a6-452a-a4f7-b9967d5f2a02",
                  "_OptionFlagAllInvisible": false,
                  "_SetIds": []
                }
              },
              {
                "ace.model_parts_manager.cGroupCondition": {
                  "_GroupId": "8c735c2d-2701-4880-819b-329a9ca152bb",
                  "_OptionFlagAllInvisible": false,
                  "_SetIds": []
                }
              }
            ],
            "_ChangeType": 1,
            "_ConditionId": "a775b43f-5f07-45a9-87af-5247c3a3cfd6",
            "_IsDefault": false
          }
        },
        {
          "ace.model_parts_manager.cConditionInfo": {
            "_GroupConditions": [
              {
                "ace.model_parts_manager.cGroupCondition": {
                  "_GroupId": "335d1d96-d593-492b-8b70-1904492c610f",
                  "_OptionFlagAllInvisible": false,
                  "_SetIds": [
                    "ce52bafd-b88e-4667-b817-0ff0131139bc"
                  ]
                }
              },
              {
                "ace.model_parts_manager.cGroupCondition": {
                  "_GroupId": "38b2c11f-735f-42cc-a4f1-59cdaafdb712",
                  "_OptionFlagAllInvisible": false,
                  "_SetIds": []
                }
              },
              {
                "ace.model_parts_manager.cGroupCondition": {
                  "_GroupId": "ad90746a-11a6-452a-a4f7-b9967d5f2a02",
                  "_OptionFlagAllInvisible": false,
                  "_SetIds": []
                }
              },
              {
                "ace.model_parts_manager.cGroupCondition": {
                  "_GroupId": "8c735c2d-2701-4880-819b-329a9ca152bb",
                  "_OptionFlagAllInvisible": false,
                  "_SetIds": []
                }
              }
            ],
            "_ChangeType": 1,
            "_ConditionId": "c875d91b-9188-4198-b6e8-fcbbe973db34",
            "_IsDefault": false
          }
        },
        {
          "ace.model_parts_manager.cConditionInfo": {
            "_GroupConditions": [
              {
                "ace.model_parts_manager.cGroupCondition": {
                  "_GroupId": "335d1d96-d593-492b-8b70-1904492c610f",
                  "_OptionFlagAllInvisible": true,
                  "_SetIds": []
                }
              },
              {
                "ace.model_parts_manager.cGroupCondition": {
                  "_GroupId": "38b2c11f-735f-42cc-a4f1-59cdaafdb712",
                  "_OptionFlagAllInvisible": false,
                  "_SetIds": []
                }
              },
              {
                "ace.model_parts_manager.cGroupCondition": {
                  "_GroupId": "ad90746a-11a6-452a-a4f7-b9967d5f2a02",
                  "_OptionFlagAllInvisible": false,
                  "_SetIds": []
                }
              },
              {
                "ace.model_parts_manager.cGroupCondition": {
                  "_GroupId": "8c735c2d-2701-4880-819b-329a9ca152bb",
                  "_OptionFlagAllInvisible": false,
                  "_SetIds": []
                }
              }
            ],
            "_ChangeType": 1,
            "_ConditionId": "aadb378f-3473-441b-b190-17b76a44e502",
            "_IsDefault": false
          }
        }
      ],
      "_PartsGroupDefinitions": {
        "ace.user_data.ModelPartsGroupDefinitions": {
          "ref_instance_id": 26,
          "path": "Art/Model/character/ch90/132_0000/mod/ch90_132_0000_mpgd.user"
        }
      }
    }
  }
]